aiomast/__init__.py
aiomast/accounts.py
aiomast/blocks.py
aiomast/bookmarks.py
aiomast/conversations.py
aiomast/domain_blocks.py
aiomast/favourites.py
aiomast/filters.py
aiomast/instance.py
aiomast/lists.py
aiomast/mutes.py
aiomast/notifications.py
aiomast/statuses.py
aiomast/timelines.py
aiomast/trends.py
aiomast/websockets.py
aiomast-0.0.4.dist-info/LICENSE
aiomast-0.0.4.dist-info/METADATA
aiomast-0.0.4.dist-info/WHEEL
aiomast-0.0.4.dist-info/top_level.txt
aiomast-0.0.4.dist-info/RECORD
