Metadata-Version: 2.1
Name: aiomast
Version: 0.0.4
Summary: Asynchronous Mastodon library for Python
Home-page: https://github.com/wybiral/aiomast
Author: davy wybiral
Author-email: davy.wybiral@gmail.com
License: MIT
Classifier: Programming Language :: Python :: 3
Classifier: License :: OSI Approved :: MIT License
Classifier: Operating System :: OS Independent
License-File: LICENSE
Requires-Dist: aiohttp
